mlx_rmvpe/__init__.py
mlx_rmvpe/model.py
mlx_rmvpe/rmvpe.py
mlx_rmvpe-0.1.0.dist-info/METADATA
mlx_rmvpe-0.1.0.dist-info/WHEEL
mlx_rmvpe-0.1.0.dist-info/top_level.txt
mlx_rmvpe-0.1.0.dist-info/RECORD
