Metadata-Version: 2.4
Name: mlx-rmvpe
Version: 0.1.0
Summary: MLX implementation of RMVPE (Robust Model for Vocal Pitch Estimation) for Apple Silicon
License: MIT
Project-URL: Homepage, https://github.com/lexandstuff/mlx-rmvpe
Project-URL: Repository, https://github.com/lexandstuff/mlx-rmvpe
Project-URL: Bug Tracker, https://github.com/lexandstuff/mlx-rmvpe/issues
Project-URL: Model Weights, https://huggingface.co/lexandstuff/mlx-rmvpe
Keywords: mlx,rmvpe,pitch,f0,audio,music,voice-conversion,rvc,apple-silicon
Classifier: Development Status :: 4 - Beta
Classifier: Intended Audience :: Developers
Classifier: Intended Audience :: Science/Research
Classifier: License :: OSI Approved :: MIT License
Classifier: Operating System :: MacOS :: MacOS X
Classifier: Programming Language :: Python :: 3
Classifier: Programming Language :: Python :: 3.11
Classifier: Programming Language :: Python :: 3.12
Classifier: Topic :: Scientific/Engineering :: Artificial Intelligence
Classifier: Topic :: Multimedia :: Sound/Audio :: Speech
Classifier: Topic :: Multimedia :: Sound/Audio :: Analysis
Requires-Python: >=3.11
Requires-Dist: huggingface-hub>=0.20.0
Requires-Dist: librosa>=0.10.0
Requires-Dist: mlx>=0.20.0
Requires-Dist: numpy>=1.24.0
Requires-Dist: safetensors>=0.4.0
Provides-Extra: dev
Requires-Dist: pytest>=8.0.0; extra == "dev"
Requires-Dist: torch>=2.0.0; extra == "dev"
Requires-Dist: ruff>=0.8.0; extra == "dev"
